Metadata-Version: 1.0
Name: umdpm
Version: 0.3
Summary: umd 包管理
Home-page: UNKNOWN
Author: wayne
Author-email: hi.wayne@qq.com
License: MIT
Keywords: swagdog
Platform: UNKNOWN
